pyclip2org/__init__.py
pyclip2org/__main__.py
pyclip2org/exporter.py
pyclip2org/parser.py
pyclip2org/py.typed
pyclip2org-0.1.1.dist-info/entry_points.txt
pyclip2org-0.1.1.dist-info/LICENSE.rst
pyclip2org-0.1.1.dist-info/WHEEL
pyclip2org-0.1.1.dist-info/METADATA
pyclip2org-0.1.1.dist-info/RECORD
