Metadata-Version: 2.1
Name: pyclip2org
Version: 0.1.1
Summary: My Clipping to org-mode notes
Home-page: https://github.com/ppalazon/pyclip2org
License: MIT
Author: Pablo Palazon
Author-email: pablo.palazon@gmail.com
Requires-Python: >=3.6.1,<4.0.0
Classifier: License :: OSI Approved :: MIT License
Classifier: Programming Language :: Python :: 3
Classifier: Programming Language :: Python :: 3.6
Classifier: Programming Language :: Python :: 3.7
Classifier: Programming Language :: Python :: 3.8
Classifier: Programming Language :: Python :: 3.9
Requires-Dist: click (>=7.0,<8.0)
Requires-Dist: python-slugify (>=4.0.1,<5.0.0)
Requires-Dist: textwrap3 (>=0.9.2,<0.10.0)
Project-URL: Changelog, https://github.com/ppalazon/pyclip2org/releases
Project-URL: Documentation, https://pyclip2org.readthedocs.io
Project-URL: Repository, https://github.com/ppalazon/pyclip2org
